field_audit/__init__.py
field_audit/apps.py
field_audit/auditors.py
field_audit/const.py
field_audit/field_audit.py
field_audit/global_context.py
field_audit/middleware.py
field_audit/models.py
field_audit/services.py
field_audit/utils.py
field_audit/management/__init__.py
field_audit/management/commands/__init__.py
field_audit/management/commands/bootstrap_field_audit_events.py
field_audit/migrations/0001_initial.py
field_audit/migrations/0002_add_is_bootstrap_column.py
field_audit/migrations/0003_alter_auditevent_change_context_and_more.py
field_audit/migrations/__init__.py
django_field_audit-1.5.0.dist-info/licenses/LICENSE
django_field_audit-1.5.0.dist-info/WHEEL
django_field_audit-1.5.0.dist-info/METADATA
django_field_audit-1.5.0.dist-info/RECORD
