Metadata-Version: 2.4
Name: django-field-audit
Version: 1.5.0
Summary: Audit Field Changes on Django Models
Author-email: Joel Miller <jmiller@dimagi.com>, Simon Kelly <simongdkelly@gmail.com>, Graham Herceg <gherceg@dimagi.com>, Chris Smit <chris.smit@dimagi.com>, Daniel Miller <millerdev@gmail.com>
Requires-Python: >=3.9
Classifier: Development Status :: 5 - Production/Stable
Classifier: Environment :: Web Environment
Classifier: Framework :: Django
Classifier: Intended Audience :: Developers
Classifier: License :: OSI Approved :: BSD License
Classifier: Operating System :: OS Independent
Classifier: Programming Language :: Python
Classifier: Programming Language :: Python :: 3
Classifier: Programming Language :: Python :: 3.9
Classifier: Programming Language :: Python :: 3.10
Classifier: Programming Language :: Python :: 3.11
Classifier: Programming Language :: Python :: 3.12
Classifier: Topic :: Software Development :: Libraries :: Python Modules
License-File: LICENSE
Requires-Dist: django>=3.2
Project-URL: Homepage, https://github.com/dimagi/django-field-audit
Project-URL: Repository, https://github.com/dimagi/django-field-audit
